pdeseg/__init__.py
pdeseg/pde_segregate.py
pdeseg-0.1.3.dist-info/WHEEL
pdeseg-0.1.3.dist-info/entry_points.txt
pdeseg-0.1.3.dist-info/METADATA
pdeseg-0.1.3.dist-info/RECORD
