Metadata-Version: 2.3
Name: pdeseg
Version: 0.1.3
Summary: A feature selection method based on identifying features that best segregate classes via their underlying probablity density estimations
Author: RenZhen95
Author-email: RenZhen95 <j-liaw@hotmail.com>
Requires-Dist: joblib>=1.5.3
Requires-Dist: matplotlib>=3.10.8
Requires-Dist: numpy<2.0.0
Requires-Dist: pandas>=2.3.3
Requires-Dist: scipy>=1.16.3
Requires-Python: >=3.11
